spdk/__init__.py
spdk/version.py
spdk/cli/__init__.py
spdk/cli/accel.py
spdk/cli/app.py
spdk/cli/bdev.py
spdk/cli/fsdev.py
spdk/cli/iobuf.py
spdk/cli/iscsi.py
spdk/cli/keyring.py
spdk/cli/log.py
spdk/cli/lvol.py
spdk/cli/misc.py
spdk/cli/nbd.py
spdk/cli/notify.py
spdk/cli/nvmf.py
spdk/cli/sock.py
spdk/cli/trace.py
spdk/cli/ublk.py
spdk/cli/vfio_user.py
spdk/cli/vhost.py
spdk/cli/vmd.py
spdk/mcp/__init__.py
spdk/mcp/server.py
spdk/rpc/__init__.py
spdk/rpc/client.py
spdk/rpc/cmd_parser.py
spdk/rpc/config.py
spdk/rpc/helpers.py
spdk/sma/__init__.py
spdk/sma/common.py
spdk/sma/qmp.py
spdk/sma/qos.py
spdk/sma/sma.py
spdk/sma/device/__init__.py
spdk/sma/device/device.py
spdk/sma/device/nvmf_tcp.py
spdk/sma/device/nvmf_vfiouser.py
spdk/sma/device/vhost_blk.py
spdk/sma/proto/.gitignore
spdk/sma/proto/__init__.py
spdk/sma/volume/__init__.py
spdk/sma/volume/crypto.py
spdk/sma/volume/crypto_bdev.py
spdk/sma/volume/volume.py
spdk/spdkcli/__init__.py
spdk/spdkcli/ui_node.py
spdk/spdkcli/ui_node_iscsi.py
spdk/spdkcli/ui_node_nvmf.py
spdk/spdkcli/ui_root.py
spdk/spdk_cli.py
spdk/spdk_rpc.py
spdk/spdk_sma.py
spdk-26.1.dist-info/METADATA
spdk-26.1.dist-info/WHEEL
spdk-26.1.dist-info/entry_points.txt
spdk-26.1.dist-info/RECORD
