Metadata-Version: 2.4
Name: spdk
Version: 26.1
Summary: Python bindings for the Storage Performance Development Kit (SPDK)
Project-URL: Homepage, https://spdk.io
Project-URL: Source, https://github.com/spdk/spdk
Project-URL: Bug Tracker, https://github.com/spdk/spdk/issues
Author-email: SPDK Authors <spdk@lists.linux.dev>
License: BSD-3-Clause
Keywords: bindings,nvme,performance,spdk,storage
Classifier: Development Status :: 5 - Production/Stable
Classifier: Intended Audience :: Developers
Classifier: License :: OSI Approved :: BSD License
Classifier: Programming Language :: Python :: 3
Classifier: Programming Language :: Python :: 3.8
Classifier: Programming Language :: Python :: 3.9
Classifier: Programming Language :: Python :: 3.10
Classifier: Programming Language :: Python :: 3.11
Classifier: Programming Language :: Python :: 3.12
Classifier: Topic :: Software Development :: Libraries :: Python Modules
Classifier: Topic :: System :: Hardware
Requires-Python: >=3.9
Provides-Extra: cli
Requires-Dist: configshell-fb; extra == 'cli'
Provides-Extra: dev
Requires-Dist: build; extra == 'dev'
Requires-Dist: grpcio; extra == 'dev'
Requires-Dist: grpcio-tools; extra == 'dev'
Requires-Dist: ijson; extra == 'dev'
Requires-Dist: jinja2; extra == 'dev'
Requires-Dist: meson; extra == 'dev'
Requires-Dist: mypy; extra == 'dev'
Requires-Dist: ninja; extra == 'dev'
Requires-Dist: pandas; extra == 'dev'
Requires-Dist: pyelftools; extra == 'dev'
Requires-Dist: python-magic; extra == 'dev'
Requires-Dist: pyyaml; extra == 'dev'
Requires-Dist: ruff; extra == 'dev'
Requires-Dist: scikit-build; (platform_machine == 'aarch64') and extra == 'dev'
Requires-Dist: tabulate; extra == 'dev'
Requires-Dist: twine; extra == 'dev'
Requires-Dist: uv; extra == 'dev'
Provides-Extra: mcp
Requires-Dist: mcp[cli]>=1.9.2; extra == 'mcp'
Provides-Extra: sma
Requires-Dist: grpcio; extra == 'sma'
Requires-Dist: protobuf; extra == 'sma'
Requires-Dist: pyyaml; extra == 'sma'
